playwright_use/__init__.py
playwright_use/cli.py
playwright_use/core/__init__.py
playwright_use/core/executor.py
playwright_use/core/healer.py
playwright_use/core/llm.py
playwright_use/core/oracle.py
playwright_use/core/planner.py
playwright_use/core/reporter.py
playwright_use/core/util.py
playwright_use-0.1.6.dist-info/licenses/LICENSE
playwright_use-0.1.6.dist-info/METADATA
playwright_use-0.1.6.dist-info/WHEEL
playwright_use-0.1.6.dist-info/entry_points.txt
playwright_use-0.1.6.dist-info/top_level.txt
playwright_use-0.1.6.dist-info/RECORD
