Metadata-Version: 2.4
Name: playwright-use
Version: 0.1.6
Summary: Natural-language UI test runner
Author: Toni Ramchandani
License: MIT
Classifier: Programming Language :: Python :: 3
Classifier: License :: OSI Approved :: MIT License
Classifier: Operating System :: OS Independent
Requires-Python: >=3.9
License-File: LICENSE
Requires-Dist: playwright>=1.43
Requires-Dist: jinja2>=3.1
Requires-Dist: python-dotenv>=1.0
Requires-Dist: PyYAML>=6.0
Requires-Dist: openai>=0.28
Provides-Extra: anthropic
Requires-Dist: anthropic>=0.34; extra == "anthropic"
Provides-Extra: groq
Requires-Dist: groq>=0.8; extra == "groq"
Dynamic: license-file
